rematch/__init__.py
rematch-0.1.dist-info/METADATA
rematch-0.1.dist-info/WHEEL
rematch-0.1.dist-info/top_level.txt
rematch-0.1.dist-info/RECORD
