Metadata-Version: 2.1
Name: rematch
Version: 0.1
Summary: regex pattern matcher
Home-page: UNKNOWN
Author: UNKNOWN
Author-email: UNKNOWN
License: UNKNOWN
Platform: UNKNOWN
